[
	{
		"title": "Start",
		"tags": "",
		"body": "- Buenos días, ¿me permiten sus billetes?\n[[ answer: |Node2]]",
		"position": {
			"x": 407,
			"y": -242
		},
		"colorID": 0
	},
	{
		"title": "Node2",
		"tags": "Ticket",
		"body": "- Aquí tiene. [[ answer: |Node3]]",
		"position": {
			"x": 404,
			"y": -23
		},
		"colorID": 0
	},
	{
		"title": "Node3",
		"tags": "",
		"body": "[[ A. ¿A dónde se dirigen? |Node4]] [[B. PERMITIR VIAJAR |Node5]]",
		"position": {
			"x": 406,
			"y": 199
		},
		"colorID": 0
	},
	{
		"title": "Node4",
		"tags": "",
		"body": "- A Denderah.\n[[ answer: |Node6]]",
		"position": {
			"x": 640,
			"y": 281
		},
		"colorID": 0
	},
	{
		"title": "Node5",
		"tags": "End",
		"body": "- Gracias. \n[[ answer: |EndNode]]",
		"position": {
			"x": 640,
			"y": 74
		},
		"colorID": 0
	},
	{
		"title": "Node6",
		"tags": "",
		"body": "[[A. PERMITIR VIAJAR|Node5]]\n[[B. Estos billetes son de otra línea|Node6_2]]",
		"position": {
			"x": 851,
			"y": 273
		},
		"colorID": 0
	},
	{
		"title": "Node8",
		"tags": "End Dropout",
		"body": "- Esto no tiene ningún sentido.\n[[ answer: |EndNode]]",
		"position": {
			"x": 965,
			"y": 56
		},
		"colorID": 0
	},
	{
		"title": "Node9",
		"tags": "End",
		"body": "- Gracias, me ocuparé de hacer llegar su buena praxis al señor Bomani.\n[[ answer: |EndNode]]",
		"position": {
			"x": 1181,
			"y": 53
		},
		"colorID": 0
	},
	{
		"title": "EndNode",
		"tags": "End",
		"body": ".",
		"position": {
			"x": 1123,
			"y": -390
		},
		"colorID": 0
	},
	{
		"title": "TalkAlreadyP1",
		"tags": "End",
		"body": "- Ya ha revisado nuestros billetes.\n[[ answer: |Node20]]",
		"position": {
			"x": 792,
			"y": -704
		},
		"colorID": 0
	},
	{
		"title": "Node20",
		"tags": "End",
		"body": "- No hay de qué.",
		"position": {
			"x": 548,
			"y": -708
		},
		"colorID": 0
	},
	{
		"title": "Node6_1",
		"tags": "",
		"body": "- En realidad, sí. No pueden viajar en este tren sin billetes válidos.\n[[ answer: |Node10]]",
		"position": {
			"x": 1032,
			"y": 876
		},
		"colorID": 0
	},
	{
		"title": "Node6_4",
		"tags": "",
		"body": "[[A. Yo solo sigo órdenes, tienen que bajar|Node8]] [[B. PERMITIR VIAJAR|Node9]]",
		"position": {
			"x": 1096,
			"y": 561
		},
		"colorID": 0
	},
	{
		"title": "Node6_2",
		"tags": "",
		"body": "- ¿Cómo? Oh, tiene razón.\n[[ answer: |Node6_3]]",
		"position": {
			"x": 643,
			"y": 502
		},
		"colorID": 0
	},
	{
		"title": "Node6_3",
		"tags": "",
		"body": "...Pero son de la misma compañía. No debería haber problema.\n[[ answer: |Node6_1]]",
		"position": {
			"x": 809,
			"y": 771
		},
		"colorID": 0
	},
	{
		"title": "Node10",
		"tags": "",
		"body": "- Los billetes son de la misma compañía y tienen el mismo destino.\n[[ answer: |Node11]]",
		"position": {
			"x": 1255,
			"y": 878
		},
		"colorID": 0
	},
	{
		"title": "Node11",
		"tags": "",
		"body": "- Ha sido un pequeño error. Sería absurdo no poder viajar por esto.\n[[ answer: |Node12]]",
		"position": {
			"x": 1472,
			"y": 876
		},
		"colorID": 0
	},
	{
		"title": "Node12",
		"tags": "",
		"body": "- No es mi decisión, sólo sigo las normas. Para viajar en el Maat Express necesitan adquirir los billetes correctos.\n[[ answer: |Node13]]",
		"position": {
			"x": 1698,
			"y": 871
		},
		"colorID": 0
	},
	{
		"title": "Node13",
		"tags": "",
		"body": "- Perdone pero soy amigo del Señor Bomani, presidente de su compañía ferroviaria...\n[[ answer: |Node14]]",
		"position": {
			"x": 1927,
			"y": 867
		},
		"colorID": 0
	},
	{
		"title": "Node14",
		"tags": "",
		"body": "...y, según él, lo primordial son los intereses del cliente.\n[[ answer: |Node15]]",
		"position": {
			"x": 1364,
			"y": 1102
		},
		"colorID": 0
	},
	{
		"title": "Node15",
		"tags": "",
		"body": "...Yo he adquirido un billete de su compañía, lo cual me convierte en su cliente. \n[[ answer: |Node16]]",
		"position": {
			"x": 1587,
			"y": 1123
		},
		"colorID": 0
	},
	{
		"title": "Node16",
		"tags": "",
		"body": "...Y si me falta al respeto, usted no está siguiendo la filosofía del señor Bomani. \n[[ answer: |Node17]]",
		"position": {
			"x": 1807,
			"y": 1128
		},
		"colorID": 0
	},
	{
		"title": "Node17",
		"tags": "",
		"body": "...Ha sido una insignificante equivocación. Teniendo en cuenta la opinión de su superior en estos asuntos, debería dejarnos viajar.\r\n[[ answer: |Node6_4]]",
		"position": {
			"x": 2030,
			"y": 1124
		},
		"colorID": 0
	}
]